MANIFEST.in
README.md
requirements.txt
setup.py
dpk/__init__.py
dpk/koopman_probabilistic.py
dpk/model_objs.py
dpk_forecast.egg-info/PKG-INFO
dpk_forecast.egg-info/SOURCES.txt
dpk_forecast.egg-info/dependency_links.txt
dpk_forecast.egg-info/requires.txt
dpk_forecast.egg-info/top_level.txt
test/testDeterministicForecast.py